# 表的构造

本节介绍表的构造。首先看下Lua官方实现中是如何处理表的构造的。我们使用如下示例代码：

```lua
{{#include ../listing/ch04.table/test_lua/table.lua}}
```

Lua语言中，如果函数只有一个参数并且是表构造，就可以省略括号`()`。跟字符串常量一样。

luac的输出如下：

```shell
$ luac -l test_lua/table.lua

main <test_lua/table.lua:0,0> (14 instructions at 0x600001820080)
0+ params, 6 slots, 1 upvalue, 1 local, 7 constants, 0 functions
	1	[1]	VARARGPREP	0
	2	[1]	LOADK    	0 0	; "kkk"
	3	[2]	GETTABUP 	1 0 1	; _ENV "print"
	4	[2]	NEWTABLE 	2 3 3	; 3
	5	[2]	EXTRAARG 	0
	6	[2]	LOADI    	3 100
	7	[2]	LOADI    	4 200
	8	[2]	LOADI    	5 300
	9	[3]	SETFIELD 	2 2 3k	; "x" "hello"
	10	[3]	SETFIELD 	2 4 5k	; "y" "world"
	11	[4]	SETTABLE 	2 0 6k	; "vvv"
	12	[5]	SETLIST  	2 3 0
	13	[2]	CALL     	1 2 1	; 1 in 0 out
	14	[5]	RETURN   	1 1 1	; 0 out
```

跟表的构造相关的字节码是第4到第12行：

- 第4行，NEWTABLE，用以创建一个表。一共3个参数，分别是新表在栈上位置，数组部分长度，和散列表部分长度。
- 第5行，忽略。
- 第6，7，8行，三个LOADI，分别加载数组部分的值100,200,300到栈上，供后面使用。
- 第9，10，11行，新字节码SETFIELD和SETTABLE，分别向散列表部分插入x、y和vvv。
- 第12行，SETLIST，把上述第6-8行加载到栈上的数据，一次性插入到数组中。

每个字节码的执行对应的栈情况如下：

```
           |       |        /<--- 9.SETFILED
           +-------+        |<---10.SETFILED
4.NEWTABLE |  { }  |<----+--+<---11.SETTABLE
           +-------+     |
   6.LOADI |  100  |---->|
           +-------+     |12.SETLIST
   7.LOADI |  200  |---->|
           +-------+     |
   8.LOADI |  300  |---->/
           +-------+
           |       |
```

首先可以看到，表的构造是在虚拟机执行过程中，通过插入逐个成员，实时构造出来的。这一点有点出乎我的意料（虽然之前并没有想过应该是什么过程）。我以前写过类似如下的代码：

```lua
local function day_of_week(day)
    local days = {
        "Sunday"=0, "Monday"=1, "Tuesday"=2,
        "Wednesday"=3, "Thursday"=4, "Friday"=5,
        "Saturday"=6,
    }
    return days[day]
end
```

代码里，把`days`这个变量放在函数内部是很自然的，因为只在这个函数内部使用。但是根据上面表的构造的实现，这么做，每次调用这个函数，都会实时构建这个表，也就是把这7个日期插入到表里，这个代价就有点大了（需要8次字符串hash和1次字符串比较，至少需要9条字节码，还有创建表带来的不止一次的内存分配）。感觉上甚至不如逐个星期名比较来的快（平均需要4次字符串比较，每次比较2条字节码一共8条）。更好的方法是把`days`这个变量放到函数外面（就是UpValue），每次进入函数就不需要构造表，但这样就把一个函数内部变量放到外面，不是好的编程习惯。另外一种做法（Lua的实现并不支持）就是对于这种全部由常量组成的表，在解析阶段就构建好，后续只要引用即可，但这么做会带来一些复杂性，后续看有没有精力完成。

回到表的构造，对于数组部分和散列表部分的处理方式是不同的：

- 数组部分，是先把值依次加载到栈上，最后一次性插入到数组中；
- 散列表部分，是每次直接插入到散列表中。

这么做的原因猜测如下：数组部分如果也逐一插入，那么有的情况需要2条字节码，比如值是全局变量，就需要先用`GetGlobal`字节码加载到栈上，然后再用一个类似`AppendTable`的字节码插入到数组中，那么插入N个值最多就需要2N条字节码。如果批量插入，N个值就只需要N+1条字节码。而对于散列表部分，每条数据有key和value两个值，每个值又有不同类型，XXX。同理，数组部分的值如果都是在常量表中，也可以增加一个`SetListConst`的字节码来处理。

这一节按照Lua官方实现方法，对应增加下面等4个字节码，并且中间两个字节码不支持常量，只支持栈上索引：

```rust,ignore
pub enum ByteCode {
    NewTable(u8, u8, u8),
    SetTable(u8, u8, u8),
    SetField(u8, u8, u8),
    SetList(u8, u8),
```

## 语法分析 

表构造可以出现在很多地方，比如变量赋值的右值，函数调用的参数等，但我们暂时只支持函数调用的特殊形式，即开头示例代码中的忽略括号`()`的形式。在下一节里再支持全部情况。

表构造的分析代码如下：

```rust,ignore
    fn table_constructor(&mut self, dst: usize) {
        let table = dst as u8;
        let inew = self.byte_codes.len();
        self.byte_codes.push(ByteCode::NewTable(table, 0, 0));

        let mut narray = 0;
        let mut nmap = 0;
        let mut sp = dst + 1;
        loop {
            match self.lex.peek() {
                Token::CurlyR => { // `}`
                    self.lex.next();
                    break;
                }
                Token::SqurL => { // `[` exp `]` `=` exp
                    nmap += 1;
                    self.lex.next();

                    self.load_exp(sp); // key
                    self.lex.expect(Token::SqurR); // `]`
                    self.lex.expect(Token::Assign); // `=`
                    self.load_exp(sp + 1); // value

                    self.byte_codes.push(ByteCode::SetTable(table, sp as u8, sp as u8 + 1));
                },
                Token::Name(_) => { // Name `=` exp
                    nmap += 1;
                    let key = if let Token::Name(key) = self.lex.next() {
                        self.add_const(key)
                    } else {
                        panic!("impossible");
                    };
                    self.lex.expect(Token::Assign); // `=`
                    self.load_exp(sp); // value

                    self.byte_codes.push(ByteCode::SetField(table, key as u8, sp as u8));
                },
                _ => { // exp
                    narray += 1;
                    self.load_exp(sp);

                    sp += 1;
                    if sp - (dst + 1) > 50 { // too many, reset it
                        self.byte_codes.push(ByteCode::SetList(table, (sp - (dst + 1)) as u8));
                        sp = dst + 1;
                    }
                },
            }

            match self.lex.next() {
                Token::SemiColon | Token::Comma => (),
                Token::CurlyR => break,
                t => panic!("invalid table {t:?}"),
            }
        }

        if sp > dst + 1 {
            self.byte_codes.push(ByteCode::SetList(table, (sp - (dst + 1)) as u8));
        }

        // reset narray and nmap
        self.byte_codes[inew] = ByteCode::NewTable(table, narray, nmap);
    }
```

代码比较长，但逻辑很简单。

函数开头生成`NewTable`字节码，但由于目前还不知道数组和散列表的成员数量，所以后面两个参数暂时填0。并记下这个字节码的位置，在函数最后修改参数。

中间循环就是遍历表的所有成员。一共3种语法类型：

- 通用式，`[ exp ] = exp`，key和value都是表达式，通过`load_exp()`函数分别加载到栈的sp和sp+1的位置，然后生成`SetTable`字节码；

- 记录式，`Name = exp`，key是Name即字符串常量，加入到常量表中，value是表达式，最后生成`SetField`字节码。这里有个地方跟Rust的所有权机制相关，就是通过`match self.lex.peek()`的模式分支`Token::Name(key)`匹配拿到的`key`是不能直接通过`add_const(*key)`添加到常量表中的。这是因为`peek()`返回的不是`Token`本身，而是`Token`的引用，这个引用是`self.lex.peek()`返回的，所以关联的`self.lex`和`self`也都处于被引用的状态；而调用`self.add_const()`也是对`self`的mut引用，就违反了引用规则。正确的做法是放弃`peek()`的返回值，而是调用`self.lex.next()`返回Token并重新匹配。这时Rust的检查显得过于严格，因为`self.lex.peek()`返回的Token引用并不会影响`self.add_const()`。应该是Rust没有能力确定这两者间没有影响。

- 列表式，`exp`，加载到栈的`sp`位置，并更新`sp`，以待最后的`SetList`执行插入。但不能无限向栈上加载数据，因为这会导致栈一直重分配内存，所以如果当前栈上数据超过50，就生成一次`SetList`字节码，清理栈。

## 虚拟机执行

下面是新增的4个字节码的虚拟机执行代码：

```rust,ignore
    ByteCode::NewTable(dst, narray, nmap) => {
        let table = Table::new(narray as usize, nmap as usize);
        self.set_stack(dst, Value::Table(Rc::new(RefCell::new(table))));
    }
    ByteCode::SetTable(table, key, value) => {
        let key = self.stack[key as usize].clone();
        let value = self.stack[value as usize].clone();
        if let Value::Table(table) = &self.stack[table as usize] {
            table.borrow_mut().map.insert(key, value);
        } else {
            panic!("not table");
        }
    }
    ByteCode::SetField(table, key, value) => {
        let key = proto.constants[key as usize].clone();
        let value = self.stack[value as usize].clone();
        if let Value::Table(table) = &self.stack[table as usize] {
            table.borrow_mut().map.insert(key, value);
        } else {
            panic!("not table");
        }
    }
    ByteCode::SetList(table, n) => {
        let ivalue = table as usize + 1;
        if let Value::Table(table) = self.stack[table as usize].clone() {
            let values = self.stack.drain(ivalue .. ivalue + n as usize);
            table.borrow_mut().array.extend(values);
        } else {
            panic!("not table");
        }
    }
```

第一个`NewTable`很简单。后面两个`SetTable`和`SetField`两个相似，需要通过`borrow_mut()`来获取表的mut引用。最后`SetList`再次遇到Rust的所有权问题。首先通过`self.stack.drain()`获取要插入到表中的栈上的数据，是迭代器类型，其中包含了对源数据（即栈）的引用；所以后续向表中插入数据时，就不用使用表的引用（就像上面两个字节码那样），而必须通过`clone()`生成一个跟栈无关的独立的表。单从语法层面讲，Rust的这个限制是必须的，因为前面生成的迭代器是可能包含表本身这个值的，如果不做这个限制那这个表就可能在插入的过程中失效，这也是C语言中常见的bug。不过从语义上讲，迭代器包含的栈范围是从表（`table`）的下一个值（`ivalue`）开始的，是不包含表本身的，但Rust是理解不了这个语义的。

## 其他场景

至此完成表的构造，可以正常执行本节开头的示例代码，但只能作为函数调用的参数，还是要不带括号`()`的特殊情况下。表构造还可以出现在另外两个场景中，即普通表达式，和作为赋值语句的右值。之所以最开始没有选择这两个场景，是因为普通表达式`load_exp()`函数的代码实现，是模式匹配`match`中，每种Token都对应一条字节码，然后在最外层push这条字节码。但表的构造是生成不止一条字节码，所以不太适合这个函数的逻辑。当然也可以通过提前退出函数来完成，如下：

```rust,ignore
    fn load_exp(&mut self, dst: usize) {
        let code = match self.lex.next() {
            Token::Nil => ByteCode::LoadNil(dst as u8),
            Token::True => ByteCode::LoadBool(dst as u8, true),
            Token::False => ByteCode::LoadBool(dst as u8, false),
            // 省略一些Token的case，比如字符串
            Token::CurlyL => { // 新增表的构造
                self.table_constructor(dst); // 并不返回一个ByteCode
                return; // 所以需要提前return
            }
            _ => panic!("invalid argument"),
        };
        self.byte_codes.push(code);
    }
```

而在赋值语句的右值中加入表的构造比较简单。但复制语句的右值本来也应该是一个普通的表达式，只不过之前为了简单起见，并没有直接调用表达式函数`load_exp()`，而是单独写了一套代码。最终还是要改为调用表达式的函数的，所以这里就算加入表的构造，也会很快被替代。

上面提到的只是两个小问题，这节表的构造的实现方式还有一个更大的问题，下一节具体描述这个问题，并通过引入`ExpDesc`来解决。